pdsketch/__init__.py
pdsketch/diagram.py
pdsketch/diagramviz.py
pdsketch/pdpoint.py
pdsketch/pdpointviz.py
pdsketch/plot_matching.py
pdsketch/sketch_style.py
pdsketch/sketchsequence.py
pdsketch-0.1.0.dist-info/LICENSE
pdsketch-0.1.0.dist-info/METADATA
pdsketch-0.1.0.dist-info/WHEEL
pdsketch-0.1.0.dist-info/top_level.txt
pdsketch-0.1.0.dist-info/RECORD
