Metadata-Version: 2.1
Name: pdsketch
Version: 0.1.0
Summary: A Python package for computing sketches of persistence diagrams.
Home-page: https://github.com/donsheehy/pdsketch
Author: Donald R. Sheehy and Siddharth Sheth
Author-email: don.r.sheehy@gmail.com
License: UNKNOWN
Platform: UNKNOWN
Classifier: Programming Language :: Python :: 3
Classifier: License :: OSI Approved :: MIT License
Classifier: Operating System :: OS Independent
Requires-Python: >=3.6
License-File: LICENSE
Requires-Dist: greedypermutation
Requires-Dist: metricspaces
